juji_python_sdk/__init__.py
juji_python_sdk/chatbot.py
juji_python_sdk/design.py
juji_python_sdk-0.2.4.dist-info/METADATA
juji_python_sdk-0.2.4.dist-info/WHEEL
juji_python_sdk-0.2.4.dist-info/RECORD
