Metadata-Version: 2.3
Name: juji-python-sdk
Version: 0.2.4
Summary: Juji Python SDK
Author: Wenxi Chen
Author-email: wchen@juji-inc.com
Requires-Python: >=3.10
Classifier: Programming Language :: Python :: 3
Classifier: Programming Language :: Python :: 3.10
Classifier: Programming Language :: Python :: 3.11
Classifier: Programming Language :: Python :: 3.12
Classifier: Programming Language :: Python :: 3.13
Requires-Dist: python-dotenv (>=1.0.1,<2.0.0)
Requires-Dist: requests (>=2.32.3,<3.0.0)
Requires-Dist: websocket-client (>=1.8.0,<2.0.0)
